pyorbital/__init__.py
pyorbital/astronomy.py
pyorbital/check_platform.py
pyorbital/fetch_tles.py
pyorbital/geoloc.py
pyorbital/geoloc_avhrr.py
pyorbital/geoloc_example.py
pyorbital/geoloc_instrument_definitions.py
pyorbital/logger.py
pyorbital/orbital.py
pyorbital/tlefile.py
pyorbital/version.py
pyorbital/etc/platforms.txt
pyorbital/tests/SGP4-VER.TLE
pyorbital/tests/__init__.py
pyorbital/tests/aiaa_results
pyorbital/tests/test_aiaa.py
pyorbital/tests/test_astronomy.py
pyorbital/tests/test_geoloc.py
pyorbital/tests/test_logging.py
pyorbital/tests/test_orbital.py
pyorbital/tests/test_tlefile.py
pyorbital-1.10.1.dist-info/METADATA
pyorbital-1.10.1.dist-info/WHEEL
pyorbital-1.10.1.dist-info/entry_points.txt
pyorbital-1.10.1.dist-info/licenses/LICENSE.txt
pyorbital-1.10.1.dist-info/RECORD
