Metadata-Version: 2.4
Name: pyorbital
Version: 1.10.1
Summary: Scheduling satellite passes in Python
Project-URL: Documentation, https://pyorbital.readthedocs.io/en/latest/
Author-email: The Pytroll Team <pytroll@googlegroups.com>
License:                     GNU GENERAL PUBLIC LICENSE
License-File: LICENSE.txt
Classifier: Development Status :: 5 - Production/Stable
Classifier: Intended Audience :: Science/Research
Classifier: License :: OSI Approved :: GNU General Public License v3 or later (GPLv3+)
Classifier: Operating System :: OS Independent
Classifier: Programming Language :: Python
Classifier: Topic :: Scientific/Engineering
Classifier: Topic :: Scientific/Engineering :: Astronomy
Requires-Python: >=3.10
Requires-Dist: defusedxml
Requires-Dist: numpy>=1.19.0
Requires-Dist: pyproj>=3.7.1
Requires-Dist: requests
Requires-Dist: scipy
Provides-Extra: doc
Requires-Dist: sphinx; extra == 'doc'
Requires-Dist: sphinx-rtd-theme; extra == 'doc'
Requires-Dist: sphinxcontrib-apidoc; extra == 'doc'
Provides-Extra: test
Requires-Dist: dask>=2025.3.0; extra == 'test'
Requires-Dist: pytest>=8.3.5; extra == 'test'
Requires-Dist: xarray>=2025.3.1; extra == 'test'
